ribomala/__init__.py
ribomala/analysis.py
ribomala/index.py
ribomala/main.py
ribomala/qc.py
ribomala-0.5.4.dist-info/licenses/LICENSE
ribomala-0.5.4.dist-info/METADATA
ribomala-0.5.4.dist-info/WHEEL
ribomala-0.5.4.dist-info/entry_points.txt
ribomala-0.5.4.dist-info/top_level.txt
ribomala-0.5.4.dist-info/RECORD
